plot3d/__init__.py
plot3d/block.py
plot3d/block_merging_mixed_facepairs.py
plot3d/blockfunctions.py
plot3d/connectivity.py
plot3d/differencing.py
plot3d/face.py
plot3d/facefunctions.py
plot3d/glennht/__init__.py
plot3d/glennht/class_definitions.py
plot3d/glennht/export_functions.py
plot3d/glennht/import_functions.py
plot3d/graph.py
plot3d/gridpro/__init__.py
plot3d/gridpro/import_functions.py
plot3d/listfunctions.py
plot3d/periodicity.py
plot3d/point_match.py
plot3d/pointwise/__init__.py
plot3d/pointwise/import_functions.py
plot3d/read.py
plot3d/split_block.py
plot3d/write.py
plot3d-1.7.14.dist-info/METADATA
plot3d-1.7.14.dist-info/WHEEL
plot3d-1.7.14.dist-info/RECORD
