Metadata-Version: 2.1
Name: plot3d
Version: 1.7.14
Summary: Plot3D python utilities for reading and writing and also finding connectivity between blocks
Author: Paht Juangphanich
Author-email: paht.juangphanich@nasa.gov
Requires-Python: >=3.10.12,<4.0.0
Classifier: Programming Language :: Python :: 3
Classifier: Programming Language :: Python :: 3.11
Classifier: Programming Language :: Python :: 3.12
Requires-Dist: matplotlib
Requires-Dist: networkx
Requires-Dist: numpy
Requires-Dist: pandas
Requires-Dist: pymetis ; platform_system != "Windows"
Requires-Dist: scipy
Requires-Dist: tqdm
